<View>
    <Header value="Speaker Categories:" />
    <Labels name="speaker_labels" toName="audio">
        <Label value="Pilot" />
        <Label value="Controller" />
    </Labels>

    <Header value="Meta Tags:" />
    <Labels name="meta_labels" toName="audio">
        <Label value="Controller Change Briefing" />
        <Label value="One-way Communication (no readback)" />
    </Labels>

    <Audio name="audio" value="$audio" />

    <Header value="Transcription:" />
    <TextArea name="transcription" toName="audio" rows="2" editable="true" perRegion="true" required="true" />
</View>